pyoauth2_util/__init__.py
pyoauth2_util/oauth2.py
pyoauth2_util-1.1.1.dist-info/LICENSE
pyoauth2_util-1.1.1.dist-info/METADATA
pyoauth2_util-1.1.1.dist-info/WHEEL
pyoauth2_util-1.1.1.dist-info/top_level.txt
pyoauth2_util-1.1.1.dist-info/zip-safe
pyoauth2_util-1.1.1.dist-info/RECORD
