Metadata-Version: 2.1
Name: pyoauth2_util
Version: 1.1.1
Summary: oauth2助手
Home-page: https://github.com/buyfakett
Author: buyfakett
Author-email: buyfakett@vip.qq.com
License: MIT
Requires-Python: >=3.6
License-File: LICENSE
Requires-Dist: fastapi
Requires-Dist: pyjwt
Requires-Dist: pyconfig-util ==1.1.0
